setup.py
ztmAPI448474/__init__.py
ztmAPI448474/analizedata.py
ztmAPI448474/getdata.py
ztmAPI448474/livefetch.py
ztmAPI448474/mapdraw.py
ztmAPI448474.egg-info/PKG-INFO
ztmAPI448474.egg-info/SOURCES.txt
ztmAPI448474.egg-info/dependency_links.txt
ztmAPI448474.egg-info/not-zip-safe
ztmAPI448474.egg-info/requires.txt
ztmAPI448474.egg-info/top_level.txt