Metadata-Version: 2.1
Name: ztmAPI448474
Version: 0.1
Summary: Fetch and analize Warsaw ztm API data
Home-page: https://github.com/kiwitrr2944/analizaAutobusowa
Author-email: wr448474@students.mimuw.edu.pl
